rooted_tree_classifier/__init__.py
rooted_tree_classifier/__main__.py
rooted_tree_classifier/common.py
rooted_tree_classifier/constant_decider.py
rooted_tree_classifier/constant_synthesizer.py
rooted_tree_classifier/log_decider.py
rooted_tree_classifier/log_star_decider.py
rooted_tree_classifier/notes.py
rooted_tree_classifier-0.2.2.dist-info/AUTHORS
rooted_tree_classifier-0.2.2.dist-info/LICENSE
rooted_tree_classifier-0.2.2.dist-info/METADATA
rooted_tree_classifier-0.2.2.dist-info/WHEEL
rooted_tree_classifier-0.2.2.dist-info/top_level.txt
rooted_tree_classifier-0.2.2.dist-info/RECORD
