Metadata-Version: 2.1
Name: rooted-tree-classifier
Version: 0.2.2
Summary: A command-line tool for automatically classifying LCL problems on rooted trees.
Home-page: https://github.com/jendas1/rooted-tree-classifier
Author: Jan Studeny
Author-email: jendas1@yahoo.com
License: Unlicense
Platform: UNKNOWN
Classifier: License :: OSI Approved :: The Unlicense (Unlicense)
Classifier: Programming Language :: Python :: 3
Classifier: Programming Language :: Python :: 3.9
Requires-Dist: networkx
Requires-Dist: z3-solver
Requires-Dist: numpy
